{
  "estatus": "OK",
  "codigoValidacion": "",
  "curp": "GAGS031227HDFRRLA3",
  "nombre": "Saul",
  "apellidoPaterno": "Garcia",
  "apellidoMaterno": "Garcia",
  "sexo": "H",
  "fechaNacimiento": "27/12/2003",
  "paisNacimiento": "Mexico",
  "estadoNacimiento": "",
  "docProbatorio": "",
  "datosDocProbatorio": {
    "anioReg": "",
    "municipioRegistro": "",
    "tomo": "",
    "libro": "",
    "numActa": "",
    "foja": "",
    "entidadRegistro": "",
    "claveEntidadRegistro": ""
  },
  "codigoMensaje": "0",
  "documento": ""
}